klldv5/__init__.py
klldv5-1.0.9.dist-info/METADATA
klldv5-1.0.9.dist-info/WHEEL
klldv5-1.0.9.dist-info/top_level.txt
klldv5-1.0.9.dist-info/RECORD
