Metadata-Version: 2.1
Name: klldv5
Version: 1.0.9
Summary: klldv5
Home-page: https://klld.42web.io
Author: klld
License: UNKNOWN
Platform: UNKNOWN
Classifier: Programming Language :: Python :: 3
Classifier: License :: OSI Approved :: MIT License
Classifier: Operating System :: OS Independent
Requires-Dist: crayons
Requires-Dist: PirxcyPinger
Requires-Dist: fortnitepy
Requires-Dist: BenBotAsync
Requires-Dist: FortniteAPIAsync
Requires-Dist: sanic
Requires-Dist: aiohttp
Requires-Dist: uvloop
Requires-Dist: requests
